{
    "type": "record",
    "name": "Task",
    "namespace": "com.tacoq.task",
    "fields": [
      {
        "name": "id",
        "type": {
          "type": "string",
          "logicalType": "uuid"
        }
      },
      {
        "name": "task_kind",
        "type": "string"
      },
      {
        "name": "worker_kind",
        "type": "string"
      },
      {
        "name": "created_at",
        "type": {
          "type": "long",
          "logicalType": "timestamp-micros"
        }
      },
      {
        "name": "started_at",
        "type": [
          "null",
          {
            "type": "long",
            "logicalType": "timestamp-micros"
          }
        ]
      },
      {
        "name": "completed_at",
        "type": [
          "null",
          {
            "type": "long",
            "logicalType": "timestamp-micros"
          }
        ]
      },
      {
        "name": "updated_at",
        "type": {
          "type": "long",
          "logicalType": "timestamp-micros"
        }
      },
      {
        "name": "input_data",
        "type": ["null", "bytes"]
      },
      {
        "name": "output_data",
        "type": [
          "null",
          "bytes"
        ]
      },
      {
        "name": "is_error",
        "type": "int"
      },
      {
        "name": "status",
        "type": {
          "type": "enum",
          "name": "TaskStatus",
          "symbols": [
            "pending",
            "processing",
            "completed"
          ]
        }
      },
      {
        "name": "priority",
        "type": "int"
      },
      {
        "name": "ttl_duration",
        "type": "long"
      },
      {
        "name": "executed_by",
        "type": [
          "null",
          "string"
        ]
      },
      {
        "name": "otel_ctx_carrier",
        "type": [
          "null",
          {
            "type": "map",
            "values": "string"
          }
        ]
      }
    ]
}
  